python_transcoded-0.4.2.dist-info/METADATA
python_transcoded-0.4.2.dist-info/RECORD
python_transcoded-0.4.2.dist-info/WHEEL
python_transcoded-0.4.2.dist-info/entry_points.txt
python_transcoded-0.4.2.dist-info/top_level.txt
transcoded/__init__.py
transcoded/__main__.py
transcoded/codecmap.py
transcoded/executor.py
transcoded/job.py
transcoded/log.py
transcoded/probe.py
transcoded/profile.py
transcoded/struct.py
transcoded/test_profile.py
transcoded/vcodec.py
