Metadata-Version: 2.1
Name: python-transcoded
Version: 0.4.2
Summary: Daemon for transcoding audio/video with an http API written in python
Home-page: https://gitlab.com/MartijnBraam/python-transcoded
Author: Martijn Braam
Author-email: martijn@brixit.nl
License: MIT
Platform: UNKNOWN
Classifier: Programming Language :: Python :: 3
Classifier: Programming Language :: Python :: 3.5
Classifier: License :: OSI Approved :: MIT License
Classifier: Operating System :: POSIX :: Linux
Classifier: Intended Audience :: System Administrators
Classifier: Topic :: Multimedia :: Video :: Conversion
Requires-Python: >=3
Requires-Dist: Werkzeug
Requires-Dist: requests
